scons_tool_gcccov-0.2.0-py3.8-nspkg.pth
sconstool/gcccov/__init__.py
sconstool/gcccov/about.py
scons_tool_gcccov-0.2.0.dist-info/METADATA
scons_tool_gcccov-0.2.0.dist-info/WHEEL
scons_tool_gcccov-0.2.0.dist-info/namespace_packages.txt
scons_tool_gcccov-0.2.0.dist-info/top_level.txt
scons_tool_gcccov-0.2.0.dist-info/RECORD
