Metadata-Version: 2.1
Name: scons-tool-gcccov
Version: 0.2.0
Summary: SCons support for gcc code coverage features
Home-page: https://github.com/ptomulik/scons-tool-gcccov
Author: Paweł Tomulik
Author-email: ptomulik@meil.pw.edu.pl
License: UNKNOWN
Platform: UNKNOWN
Requires-Python: >=2.7
